smars_library/__init__.py
smars_library/channel.py
smars_library/morse.py
smars_library/smars_library.py
smars_library-1.0.8.dist-info/LICENSE
smars_library-1.0.8.dist-info/METADATA
smars_library-1.0.8.dist-info/WHEEL
smars_library-1.0.8.dist-info/top_level.txt
smars_library-1.0.8.dist-info/RECORD
