Metadata-Version: 2.1
Name: smars-library
Version: 1.0.8
Summary: SMARS Robot Python Library
Home-page: https://github.com/kevinmcaleer/smars_library
Author: Kevin McAleer
Author-email: kevinmcaleer@gmail.com
License: MIT
Platform: UNKNOWN
Classifier: License :: OSI Approved :: MIT License
Classifier: Programming Language :: Python :: 3
Classifier: Programming Language :: Python :: 3.7
Classifier: Programming Language :: Python :: 3.8
Classifier: Programming Language :: Python :: 3.9
License-File: LICENSE
Requires-Dist: adafruit-pca9685
Requires-Dist: pathlib
